jutsu_api/__init__.py
jutsu_api-2.4.dist-info/LICENSE.txt
jutsu_api-2.4.dist-info/METADATA
jutsu_api-2.4.dist-info/WHEEL
jutsu_api-2.4.dist-info/top_level.txt
jutsu_api-2.4.dist-info/RECORD
