Metadata-Version: 2.1
Name: jutsu-api
Version: 2.4
Summary: Simple and flexible API for jut.su
Author-email: dev_null <natgaev@gmail.com>
Project-URL: Homepage, https://github.com/gxlg/jutsu-api
Project-URL: Bug Tracker, https://github.com/gxlg/jutsu-api/issues
Classifier: Programming Language :: Python :: 3
Classifier: License :: OSI Approved :: MIT License
Classifier: Operating System :: OS Independent
Requires-Python: >=3.10
License-File: LICENSE.txt
Requires-Dist: requests
